cobstickettoy-0.2.1.dist-info/METADATA
cobstickettoy-0.2.1.dist-info/WHEEL
cobstickettoy-0.2.1.dist-info/entry_points.txt
cobstickettoy-0.2.1.dist-info/licenses/LICENSE
cobstickettoy/__init__.py
cobstickettoy/cobstickettoy.py
cobstickettoy-0.2.1.dist-info/RECORD
