Metadata-Version: 2.1
Name: CobsTicketToy
Version: 0.2.1
Summary: It's about my hobby
Author-Email: jacob-53 <jacob8753@gmail.com>
License: MIT
Requires-Python: >=3.10
Requires-Dist: typer>=0.15.1
Requires-Dist: pandas>=2.2.3
